LICENSE
PKG-INFO
README.md
__init__.py
gupy_framework_macos_deps.py
macos.7z
pyproject.toml
requirements.txt
gupy_framework_macos_deps/LICENSE
gupy_framework_macos_deps/README.md
gupy_framework_macos_deps/__init__.py
gupy_framework_macos_deps/gupy_framework_macos_deps.py
gupy_framework_macos_deps/macos.7z
gupy_framework_macos_deps/pyproject.toml
gupy_framework_macos_deps/requirements.txt
gupy_framework_macos_deps-0.0.3.dist-info/METADATA
gupy_framework_macos_deps-0.0.3.dist-info/WHEEL
gupy_framework_macos_deps-0.0.3.dist-info/licenses/LICENSE
gupy_framework_macos_deps-0.0.3.dist-info/RECORD
