Metadata-Version: 2.4
Name: gupy_framework_macos_deps
Version: 0.0.3
Summary: A small example package
Project-URL: Homepage, https://github.com/pypa/sampleproject
Project-URL: Issues, https://github.com/pypa/sampleproject/issues
Author-email: Example Author <author@example.com>
License-File: LICENSE
Classifier: License :: OSI Approved :: MIT License
Classifier: Operating System :: OS Independent
Classifier: Programming Language :: Python :: 3
Requires-Python: >=3.11
Requires-Dist: brotli==1.1.0
Requires-Dist: inflate64==1.0.1
Requires-Dist: multivolumefile==0.2.3
Requires-Dist: psutil==7.0.0
Requires-Dist: py7zr==0.22.0
Requires-Dist: pybcj==1.0.3
Requires-Dist: pycryptodomex==3.22.0
Requires-Dist: pyppmd==1.1.1
Requires-Dist: pyzstd==0.16.2
Requires-Dist: texttable==1.7.0
